ichi_server/__init__.py
ichi_server/__main__.py
ichi_server/alembic.ini
ichi_server/dependencies.py
ichi_server/manager.py
ichi_server/server.py
ichi_server/version.py
ichi_server/migrations/env.py
ichi_server/migrations/script.py.mako
ichi_server/migrations/versions/2022_11_27_2313-401e7f4a7484_initial.py
ichi_server/migrations/versions/2023_04_16_0335-8f378bcf99e0_update_ban_and_mute_fields.py
ichi_server/migrations/versions/2023_05_21_2212-5c40158bd1fd_remove_chat_color_field.py
ichi_server/migrations/versions/2023_06_14_2158-8c0d65bbd65a_add_admin_state_field_to_user.py
ichi_server/models/__init__.py
ichi_server/models/account.py
ichi_server/models/client.py
ichi_server/models/exceptions.py
ichi_server/models/misc.py
ichi_server/models/room.py
ichi_server/models/gamemodes/__init__.py
ichi_server/models/gamemodes/base.py
ichi_server/models/gamemodes/debug.py
ichi_server/models/gamemodes/ichi.py
ichi_server/resources/SpaceMono-Regular.ttf
ichi_server/resources/watermark.png
ichi_server/resources/game_mode_images/ichi.webp
ichi_server/resources/game_mode_images/ichi07.webp
ichi_server/resources/static/logo.svg
ichi_server/resources/static/swagger-ui-bundle-min.js
ichi_server/resources/static/swagger-ui.css
ichi_server/routers/__init__.py
ichi_server/routers/account.py
ichi_server/routers/admin.py
ichi_server/routers/captcha.py
ichi_server/routers/debug.py
ichi_server/routers/gamemode.py
ichi_server-3.0.dist-info/LICENSE
ichi_server-3.0.dist-info/WHEEL
ichi_server-3.0.dist-info/METADATA
ichi_server-3.0.dist-info/RECORD
