Metadata-Version: 2.1
Name: ichi-server
Version: 3.0
Summary: An ichi server written in Python
Author-email: aveeryy <aveeryy@protonmail.com>
Requires-Python: >=3.10
Classifier: Programming Language :: Python :: 3
Classifier: Programming Language :: Python :: 3.10
Classifier: Programming Language :: Python :: 3.11
Requires-Dist: fastapi==0.101.0
Requires-Dist: hypercorn==0.14.4
Requires-Dist: sqlmodel==0.0.8
Requires-Dist: SQLAlchemy==1.4.41
Requires-Dist: pydantic==1.10.7
Requires-Dist: passlib[bcrypt]==1.7.4
Requires-Dist: aiofiles==23.2.1
Requires-Dist: python-multipart==0.0.6
Requires-Dist: colorama==0.4.6
Requires-Dist: Pillow==10.0.0
Requires-Dist: ichi-auth==1.1
Requires-Dist: alembic==1.11.2
Requires-Dist: python-dotenv==1.0.0
Requires-Dist: flit==3.9.0 ; extra == "build"
Requires-Dist: Nuitka>=1.2.3 ; extra == "build"
Requires-Dist: zstandard>=0.19.0 ; extra == "build"
Requires-Dist: pytest==7.2.1 ; extra == "tests"
Requires-Dist: pytest-asyncio==0.20.3 ; extra == "tests"
Requires-Dist: httpx==0.23.3 ; extra == "tests"
Project-URL: Home, https://codeberg.org/ichi/server
Provides-Extra: build
Provides-Extra: tests
